jellyproxy/__init__.py
jellyproxy/config.py
jellyproxy/main.py
jellyproxy/proxy.py
jellyproxy-0.1.1.dist-info/METADATA
jellyproxy-0.1.1.dist-info/WHEEL
jellyproxy-0.1.1.dist-info/entry_points.txt
jellyproxy-0.1.1.dist-info/top_level.txt
jellyproxy-0.1.1.dist-info/RECORD
