Metadata-Version: 2.4
Name: jellyproxy
Version: 0.1.1
Summary: Jellyfin MPV IPC Proxy & Filter - Intercept and filter IPC communication between jellyfin-mpv-shim and mpv
Author: John Dovern
Maintainer: John Dovern
License: GPL-3.0-or-later
Project-URL: Homepage, https://github.com/johndovern/JellyProxy
Project-URL: Repository, https://github.com/johndovern/JellyProxy
Project-URL: Issues, https://github.com/johndovern/JellyProxy/issues
Project-URL: Documentation, https://github.com/johndovern/JellyProxy#readme
Keywords: mpv,jellyfin,proxy,ipc,media,filtering
Classifier: Development Status :: 3 - Alpha
Classifier: Intended Audience :: End Users/Desktop
Classifier: License :: OSI Approved :: GNU General Public License v3 or later (GPLv3+)
Classifier: Operating System :: POSIX :: Linux
Classifier: Programming Language :: Python :: 3
Classifier: Programming Language :: Python :: 3.8
Classifier: Programming Language :: Python :: 3.9
Classifier: Programming Language :: Python :: 3.10
Classifier: Programming Language :: Python :: 3.11
Classifier: Programming Language :: Python :: 3.12
Classifier: Topic :: Multimedia :: Video
Classifier: Topic :: System :: Networking
Requires-Python: >=3.8
Requires-Dist: python-mpv-jsonipc>=1.2.1
Provides-Extra: dev
Requires-Dist: pytest>=7.0.0; extra == "dev"
Requires-Dist: pytest-asyncio>=0.21.0; extra == "dev"
Requires-Dist: black>=22.0.0; extra == "dev"
Requires-Dist: flake8>=4.0.0; extra == "dev"
Requires-Dist: mypy>=0.991; extra == "dev"
Provides-Extra: test
Requires-Dist: pytest>=7.0.0; extra == "test"
Requires-Dist: pytest-asyncio>=0.21.0; extra == "test"
Requires-Dist: pytest-cov>=4.0.0; extra == "test"
